README.md
setup.py
vboUtil/__init__.py
vboUtil/eda.py
vboUtil/methods.py
vboUtil/preprocessing.py
vboUtil.egg-info/PKG-INFO
vboUtil.egg-info/SOURCES.txt
vboUtil.egg-info/dependency_links.txt
vboUtil.egg-info/requires.txt
vboUtil.egg-info/top_level.txt