Metadata-Version: 2.1
Name: vboUtil
Version: 0.1.2
Summary: Functions given in the VBO Bootcamp
Home-page: UNKNOWN
Author: Mehmet OZER
License: MIT
Platform: UNKNOWN
